{"config": {"range": {"category": ["#4c78a8", "#9ecae9", "#f58518", "#ffbf79", "#54a24b", "#88d27a", "#b79a20", "#f2cf5b", "#439894", "#83bcb6", "#e45756", "#ff9d98", "#79706e", "#bab0ac", "#d67195", "#fcbfd2", "#b279a2", "#d6a5c9", "#9e765f", "#d8b5a5"]}}, "data": {"url": "data/20442.tsv"}, "mark": "bar", "encoding": {"color": {"value": "#54a24b"}, "x": {"type": "nominal", "axis": {"labelAngle": 45}, "bin": false, "field": "Year"}, "y": {"type": "quantitative", "axis": {"title": "Share operated by full owners"}, "field": "Share operated by full owners"}}, "title": ["Percentage of United States farmland operated", "by full land owners from 1925 to 2012"], "$schema": "https://vega.github.io/schema/vega-lite/v4.8.1.json"}